markdantic/__init__.py
markdantic/functions.py
markdantic/generator.py
markdantic/models.py
markdantic/py.typed
markdantic/templates/model.md.j2
markdantic-0.1.0.dist-info/licenses/LICENSE
markdantic-0.1.0.dist-info/METADATA
markdantic-0.1.0.dist-info/WHEEL
markdantic-0.1.0.dist-info/top_level.txt
markdantic-0.1.0.dist-info/RECORD
