Metadata-Version: 2.4
Name: markdantic
Version: 0.1.0
Summary: Generate Markdown-formatted text based on a Pydantic model.
Author-email: Taizo Munemura <github@velvet.sakura.ne.jp>
License-Expression: MIT
Requires-Python: >=3.11
License-File: LICENSE
Requires-Dist: jinja2>=3.1.6
Requires-Dist: pydantic>=2.12.5
Dynamic: license-file
